RGBMatrixDriver/__init__.py
RGBMatrixDriver/arguments.py
RGBMatrixDriver/driver.py
RGBMatrixDriver/logger.py
RGBMatrixDriver/matrix.py
RGBMatrixDriver/options.py
RGBMatrixDriver/version.py
RGBMatrixDriver/fonts/4x6.bdf
rgbmatrixdriver-0.1.3.data/data/docs/LICENSE
rgbmatrixdriver-0.1.3.data/data/docs/README.md
rgbmatrixdriver-0.1.3.dist-info/METADATA
rgbmatrixdriver-0.1.3.dist-info/WHEEL
rgbmatrixdriver-0.1.3.dist-info/licenses/LICENSE
rgbmatrixdriver-0.1.3.dist-info/RECORD
